<annotation>
	<folder>images-raw</folder>
	<filename>BOOK-0824731-0088.jpg</filename>
	<path>C:\Users\vanny 2\Desktop\BOOK-ZID0824731\images-raw\BOOK-0824731-0088.jpg</path>
	<source>
		<database>Unknown</database>
	</source>
	<size>
		<width>6271</width>
		<height>4333</height>
		<depth>3</depth>
	</size>
	<segmented>0</segmented>
	<object>
		<name>animal</name>
		<pose>Unspecified</pose>
		<truncated>0</truncated>
		<difficult>0</difficult>
		<bndbox>
			<xmin>2005</xmin>
			<ymin>3096</ymin>
			<xmax>2891</xmax>
			<ymax>3663</ymax>
		</bndbox>
	</object>
	<object>
		<name>human</name>
		<pose>Unspecified</pose>
		<truncated>0</truncated>
		<difficult>0</difficult>
		<bndbox>
			<xmin>3491</xmin>
			<ymin>2869</ymin>
			<xmax>3911</xmax>
			<ymax>3516</ymax>
		</bndbox>
	</object>
	<object>
		<name>human</name>
		<pose>Unspecified</pose>
		<truncated>0</truncated>
		<difficult>0</difficult>
		<bndbox>
			<xmin>4231</xmin>
			<ymin>3083</ymin>
			<xmax>4465</xmax>
			<ymax>3396</ymax>
		</bndbox>
	</object>
	<object>
		<name>human</name>
		<pose>Unspecified</pose>
		<truncated>0</truncated>
		<difficult>0</difficult>
		<bndbox>
			<xmin>4585</xmin>
			<ymin>2989</ymin>
			<xmax>4885</xmax>
			<ymax>3643</ymax>
		</bndbox>
	</object>
</annotation>
